lexoffice_py/__init__.py
lexoffice_py/client.py
lexoffice_py/custom_types.py
lexoffice_py/errors.py
lexoffice_py-0.0.7.dist-info/LICENSE
lexoffice_py-0.0.7.dist-info/METADATA
lexoffice_py-0.0.7.dist-info/WHEEL
lexoffice_py-0.0.7.dist-info/top_level.txt
lexoffice_py-0.0.7.dist-info/RECORD
