Metadata-Version: 2.2
Name: lexoffice_py
Version: 0.0.7
Summary: A python wrapper around the lexoffice api.
Author-email: Friedrich ten Hagen <author@example.com>
Project-URL: Homepage, https://github.com/FriedrichtenHagen/lexoffice_py
Project-URL: Issues, https://github.com/FriedrichtenHagen/lexoffice_py/issues
Classifier: Programming Language :: Python :: 3
Classifier: License :: OSI Approved :: MIT License
Classifier: Operating System :: OS Independent
Requires-Python: >=3.8
License-File: LICENSE
Requires-Dist: requests>=2.0.0
Provides-Extra: test
Requires-Dist: pytest; extra == "test"
Requires-Dist: pytest-mock; extra == "test"
Requires-Dist: responses; extra == "test"
